{"type":"FeatureCollection", "features": [
{"type":"Feature","geometry":{"type":"Polygon","coordinates":[[[83.93326569,27.44940567],[86.14894104,26.60845566],[86.51802826,27.95632744],[85.11038208,28.34679604],[83.93326569,27.44940567]]]},"properties":{"GID_0":"NPL","NAME_0":"Nepal","GID_1":"NPL.1_1","NAME_1":"Central","VARNAME_1":"Madhyamanchal","NL_NAME_1":"मध्यमाञ्चल विकास क्षेत्र","TYPE_1":"Vikas Kshetra","ENGTYPE_1":"Development Region","CC_1":"","HASC_1":"NP.MM","cXId":"MM"}},
{"type":"Feature","geometry":{"type":"Polygon","coordinates":[[[86.14894104,26.60845566],[88.0296936,26.38153267],[88.20392609,27.83731461],[86.51802826,27.95632744],[86.14894104,26.60845566]]]},"properties":{"GID_0":"NPL","NAME_0":"Nepal","GID_1":"NPL.2_1","NAME_1":"East","VARNAME_1":"Eastern|Purwanchal","NL_NAME_1":"पुर्वाञ्चल विकास क्षेत्र","TYPE_1":"Vikas Kshetra","ENGTYPE_1":"Development Region","CC_1":"","HASC_1":"NP.PW","cXId":"PW"}},
{"type":"Feature","geometry":{"type":"Polygon","coordinates":[[[81.06912994,28.39439201],[81.27581787,30.04451561],[80.06014252,28.91631699],[81.06912994,28.39439201]]]},"properties":{"GID_0":"NPL","NAME_0":"Nepal","GID_1":"NPL.3_1","NAME_1":"Far-Western","VARNAME_1":"Sudur Pashchimanchal","NL_NAME_1":"सुदुर पश्चिमाञ्चल विकास क्षेत्र","TYPE_1":"Vikas Kshetra","ENGTYPE_1":"Development Region","CC_1":"","HASC_1":"NP.SP","cXId":"SP"}},
{"type":"Feature","geometry":{"type":"Polygon","coordinates":[[[81.06912994,28.39439201],[82.70991516,27.72169876],[83.65952301,29.17610931],[81.27581787,30.04451561],[81.06912994,28.39439201]]]},"properties":{"GID_0":"NPL","NAME_0":"Nepal","GID_1":"NPL.4_1","NAME_1":"Mid-Western","VARNAME_1":"Madhya Pashchimanchal","NL_NAME_1":"मध्य पश्चिमाञ्चल विकास क्षेत्र","TYPE_1":"Vikas Kshetra","ENGTYPE_1":"Development Region","CC_1":"","HASC_1":"NP.MP","cXId":"MP"}},
{"type":"Feature","geometry":{"type":"Polygon","coordinates":[[[82.70991516,27.72169876],[83.93326569,27.44940567],[85.11038208,28.34679604],[83.65952301,29.17610931],[82.70991516,27.72169876]]]},"properties":{"GID_0":"NPL","NAME_0":"Nepal","GID_1":"NPL.5_1","NAME_1":"West","VARNAME_1":"Western|Pashchimanchal","NL_NAME_1":"पश्चिमाञ्चल विकास क्षेत्र","TYPE_1":"Vikas Kshetra","ENGTYPE_1":"Development Region","CC_1":"","HASC_1":"NP.PM","cXId":"PM"}}
]}