{"type":"FeatureCollection", "features": [
{"type":"Feature","geometry":{"type":"Polygon","coordinates":[[[9.97027206,36.93235016],[10.08026409,36.82851028],[10.2304163,36.95763779],[10.14347076,37.13139343],[9.97027206,36.93235016]]]},"properties":{"GID_0":"TUN","NAME_0":"Tunisia","GID_1":"TUN.1_1","NAME_1":"Ariana","VARNAME_1":"Al Aryiānah|L'Ariana|Tunis Ariana|Al Aryānah","NL_NAME_1":"","TYPE_1":"Wilayat","ENGTYPE_1":"Governorate","CC_1":"","HASC_1":"TN.AN","cXId":"AN"}},
{"type":"Feature","geometry":{"type":"Polygon","coordinates":[[[9.00100708,36.47401047],[9.73458958,36.46102905],[9.84553814,36.59164047],[9.55673122,36.85232925],[9.08780289,37.15874863],[8.90486145,37.02323151],[9.00100708,36.47401047]]]},"properties":{"GID_0":"TUN","NAME_0":"Tunisia","GID_1":"TUN.2_1","NAME_1":"Béja","VARNAME_1":"Bājah|Béja","NL_NAME_1":"","TYPE_1":"Wilayat","ENGTYPE_1":"Governorate","CC_1":"","HASC_1":"TN.BJ","cXId":"BJ"}},
{"type":"Feature","geometry":{"type":"Polygon","coordinates":[[[10.38527203,36.71708298],[10.20784092,36.77902603],[10.04176044,36.72344971],[9.97170162,36.66345978],[10.33234119,36.50741959],[10.38527203,36.71708298]]]},"properties":{"GID_0":"TUN","NAME_0":"Tunisia","GID_1":"TUN.3_1","NAME_1":"Ben Arous (Tunis Sud)","VARNAME_1":"Bin `Arūs|Ben Arous|Tunis Ben Arous","NL_NAME_1":"","TYPE_1":"Wilayat","ENGTYPE_1":"Governorate","CC_1":"","HASC_1":"TN.BA","cXId":"BA"}},
{"type":"Feature","geometry":{"type":"Polygon","coordinates":[[[9.08780289,37.15874863],[9.55673122,36.85232925],[9.97027206,36.93235016],[10.14347076,37.13139343],[9.66652775,37.33847046],[9.08780289,37.15874863]]]},"properties":{"GID_0":"TUN","NAME_0":"Tunisia","GID_1":"TUN.4_1","NAME_1":"Bizerte","VARNAME_1":"BanzartBanzart|Bensert|Binzart|Biserta|Bizerta","NL_NAME_1":"","TYPE_1":"Wilayat","ENGTYPE_1":"Governorate","CC_1":"","HASC_1":"TN.BZ","cXId":"BZ"}},
{"type":"Feature","geometry":{"type":"Polygon","coordinates":[[[9.70484734,33.30070114],[10.00687122,33.30751038],[10.45621204,33.66213989],[10.02251339,34.17069626],[9.69743347,34.29526138],[9.57936668,34.30628967],[9.25545597,34.21031189],[9.25354862,33.8884201],[9.70484734,33.30070114]]]},"properties":{"GID_0":"TUN","NAME_0":"Tunisia","GID_1":"TUN.5_1","NAME_1":"Gabès","VARNAME_1":"Qābis|Gabās","NL_NAME_1":"","TYPE_1":"Wilayat","ENGTYPE_1":"Governorate","CC_1":"","HASC_1":"TN.GB","cXId":"GB"}},
{"type":"Feature","geometry":{"type":"Polygon","coordinates":[[[9.57936668,34.30628967],[9.21404362,34.70483017],[8.80420303,34.77381134],[8.29657078,34.74994659],[8.12983704,34.52702713],[8.04351234,34.31679916],[8.65681171,34.08311844],[9.25545597,34.21031189],[9.57936668,34.30628967]]]},"properties":{"GID_0":"TUN","NAME_0":"Tunisia","GID_1":"TUN.6_1","NAME_1":"Gafsa","VARNAME_1":"Gafṣah|Qafṣah","NL_NAME_1":"","TYPE_1":"Wilayat","ENGTYPE_1":"Governorate","CC_1":"","HASC_1":"TN.GF","cXId":"GF"}},
{"type":"Feature","geometry":{"type":"Polygon","coordinates":[[[8.92332458,36.46094131],[9.00100708,36.47401047],[8.90486145,37.02323151],[8.64513779,36.94319534],[8.39275837,36.36610413],[8.92332458,36.46094131]]]},"properties":{"GID_0":"TUN","NAME_0":"Tunisia","GID_1":"TUN.7_1","NAME_1":"Jendouba","VARNAME_1":"Jendoûbah|Jenduba|Jondouba|Jundūbah|Souk-El-Arba|Dschunduba","NL_NAME_1":"","TYPE_1":"Wilayat","ENGTYPE_1":"Governorate","CC_1":"","HASC_1":"TN.JE","cXId":"JE"}},
{"type":"Feature","geometry":{"type":"Polygon","coordinates":[[[9.43677139,35.51092148],[10.03967953,35.03701019],[10.22017956,35.16584015],[10.30322075,35.59817886],[10.19923019,36.16115189],[9.7273674,36.09008026],[9.48654938,35.91923904],[9.43677139,35.51092148]]]},"properties":{"GID_0":"TUN","NAME_0":"Tunisia","GID_1":"TUN.8_1","NAME_1":"Kairouan","VARNAME_1":"Al Qayrawān|Al Qīrwān|Qairouân|Kairuã|Kairouwan","NL_NAME_1":"","TYPE_1":"Wilayat","ENGTYPE_1":"Governorate","CC_1":"","HASC_1":"TN.KR","cXId":"KR"}},
{"type":"Feature","geometry":{"type":"Polygon","coordinates":[[[8.29657078,34.74994659],[8.80420303,34.77381134],[9.26544094,35.03763962],[9.32386684,35.49259949],[8.99580574,35.71350098],[8.36088467,35.63482666],[8.45840454,35.22275162],[8.29657078,34.74994659]]]},"properties":{"GID_0":"TUN","NAME_0":"Tunisia","GID_1":"TUN.9_1","NAME_1":"Kassérine","VARNAME_1":"Al Qaṣrayn|Al Gaṣrīn|Al Qasrin|Kasserim|Al Qaṣrayn|Sbeitla","NL_NAME_1":"","TYPE_1":"Wilayat","ENGTYPE_1":"Governorate","CC_1":"","HASC_1":"TN.KS","cXId":"KS"}},
{"type":"Feature","geometry":{"type":"Polygon","coordinates":[[[9.70484734,33.30070114],[9.25354862,33.8884201],[9.25545597,34.21031189],[8.65681171,34.08311844],[8.54672718,33.92374039],[7.75341892,33.43026352],[8.11796379,33.09938049],[8.35474491,32.52820587],[9.66339874,32.80627823],[9.92028522,33.0891304],[9.70484734,33.30070114]]]},"properties":{"GID_0":"TUN","NAME_0":"Tunisia","GID_1":"TUN.10_1","NAME_1":"Kebili","VARNAME_1":"Kebilli|Qbili|Qibilī","NL_NAME_1":"","TYPE_1":"Wilayat","ENGTYPE_1":"Governorate","CC_1":"","HASC_1":"TN.KB","cXId":"KB"}},
{"type":"Feature","geometry":{"type":"Polygon","coordinates":[[[8.99580574,35.71350098],[9.15082264,36.0093689],[8.92332458,36.46094131],[8.39275837,36.36610413],[8.25826454,35.90875244],[8.36088467,35.63482666],[8.99580574,35.71350098]]]},"properties":{"GID_0":"TUN","NAME_0":"Tunisia","GID_1":"TUN.11_1","NAME_1":"Le Kef","VARNAME_1":"Al Kāf|El Kef|Kaf|Kef","NL_NAME_1":"","TYPE_1":"Wilayat","ENGTYPE_1":"Governorate","CC_1":"","HASC_1":"TN.KF","cXId":"KF"}},
{"type":"Feature","geometry":{"type":"Polygon","coordinates":[[[10.22017956,35.16584015],[10.76066113,35.28862],[11.02319527,35.10634995],[11.03264046,35.57898331],[10.59437084,35.50740051],[10.30322075,35.59817886],[10.22017956,35.16584015]]]},"properties":{"GID_0":"TUN","NAME_0":"Tunisia","GID_1":"TUN.12_1","NAME_1":"Mahdia","VARNAME_1":"Al Madīyah|Al Mahdiyya|Mahdiâh","NL_NAME_1":"","TYPE_1":"Wilayat","ENGTYPE_1":"Governorate","CC_1":"","HASC_1":"TN.MH","cXId":"MH"}},
{"type":"Feature","geometry":{"type":"Polygon","coordinates":[[[9.55673122,36.85232925],[9.84553814,36.59164047],[9.97170162,36.66345978],[10.04176044,36.72344971],[10.08026409,36.82851028],[9.97027206,36.93235016],[9.55673122,36.85232925]]]},"properties":{"GID_0":"TUN","NAME_0":"Tunisia","GID_1":"TUN.13_1","NAME_1":"Manubah","VARNAME_1":"","NL_NAME_1":"","TYPE_1":"Wilayat","ENGTYPE_1":"Governorate","CC_1":"","HASC_1":"TN.MN","cXId":"MN"}},
{"type":"Feature","geometry":{"type":"Polygon","coordinates":[[[11.14614964,32.25342941],[11.52731895,32.40280914],[11.56445789,33.16541672],[11.18819523,33.20180511],[10.91874886,33.66930389],[10.45621204,33.66213989],[10.00687122,33.30751038],[9.70484734,33.30070114],[9.92028522,33.0891304],[10.50236893,33.27481079],[10.99125099,33.06560135],[11.06365871,32.69675064],[11.3445797,32.50769043],[11.14614964,32.25342941]]]},"properties":{"GID_0":"TUN","NAME_0":"Tunisia","GID_1":"TUN.14_1","NAME_1":"Médenine","VARNAME_1":"Madanīyīn|Madanīn|Medenin","NL_NAME_1":"","TYPE_1":"Wilayat","ENGTYPE_1":"Governorate","CC_1":"","HASC_1":"TN.ME","cXId":"ME"}},
{"type":"Feature","geometry":{"type":"Polygon","coordinates":[[[10.59437084,35.50740051],[11.03264046,35.57898331],[10.66295242,35.80425644],[10.59437084,35.50740051]]]},"properties":{"GID_0":"TUN","NAME_0":"Tunisia","GID_1":"TUN.15_1","NAME_1":"Monastir","VARNAME_1":"Al Munastīr","NL_NAME_1":"","TYPE_1":"Wilayat","ENGTYPE_1":"Governorate","CC_1":"","HASC_1":"TN.MS","cXId":"MS"}},
{"type":"Feature","geometry":{"type":"Polygon","coordinates":[[[10.53680515,36.36347198],[10.91791916,36.6496315],[11.0462513,37.08263779],[10.38527203,36.71708298],[10.33234119,36.50741959],[10.35482883,36.39509964],[10.53680515,36.36347198]]]},"properties":{"GID_0":"TUN","NAME_0":"Tunisia","GID_1":"TUN.16_1","NAME_1":"Nabeul","VARNAME_1":"Cap Bon|Nabil|Nābol|Nābul","NL_NAME_1":"","TYPE_1":"Wilayat","ENGTYPE_1":"Governorate","CC_1":"","HASC_1":"TN.NB","cXId":"NB"}},
{"type":"Feature","geometry":{"type":"Polygon","coordinates":[[[10.02251339,34.17069626],[10.86569309,34.81430435],[11.02319527,35.10634995],[10.76066113,35.28862],[10.22017956,35.16584015],[10.03967953,35.03701019],[9.69743347,34.29526138],[10.02251339,34.17069626]]]},"properties":{"GID_0":"TUN","NAME_0":"Tunisia","GID_1":"TUN.17_1","NAME_1":"Sfax","VARNAME_1":"Safāqis|Ṣafāqis|Ṣfāqis","NL_NAME_1":"","TYPE_1":"Wilayat","ENGTYPE_1":"Governorate","CC_1":"","HASC_1":"TN.SF","cXId":"SF"}},
{"type":"Feature","geometry":{"type":"Polygon","coordinates":[[[9.69743347,34.29526138],[10.03967953,35.03701019],[9.43677139,35.51092148],[9.32386684,35.49259949],[9.26544094,35.03763962],[8.80420303,34.77381134],[9.21404362,34.70483017],[9.57936668,34.30628967],[9.69743347,34.29526138]]]},"properties":{"GID_0":"TUN","NAME_0":"Tunisia","GID_1":"TUN.18_1","NAME_1":"Sidi Bou Zid","VARNAME_1":"Sīdī Bū Zayd|Qamudah|Sidi Boû Sa`îd|Sidi Buzid|Sidi Bū Sa`īd|Sīdī Bū Zayd|Sidi Bu Said","NL_NAME_1":"","TYPE_1":"Wilayat","ENGTYPE_1":"Governorate","CC_1":"","HASC_1":"TN.SZ","cXId":"SZ"}},
{"type":"Feature","geometry":{"type":"Polygon","coordinates":[[[9.43677139,35.51092148],[9.48654938,35.91923904],[9.7273674,36.09008026],[9.73458958,36.46102905],[9.00100708,36.47401047],[8.92332458,36.46094131],[9.15082264,36.0093689],[8.99580574,35.71350098],[9.32386684,35.49259949],[9.43677139,35.51092148]]]},"properties":{"GID_0":"TUN","NAME_0":"Tunisia","GID_1":"TUN.19_1","NAME_1":"Siliana","VARNAME_1":"Siliānah|Silyānah","NL_NAME_1":"","TYPE_1":"Wilayat","ENGTYPE_1":"Governorate","CC_1":"","HASC_1":"TN.SL","cXId":"SL"}},
{"type":"Feature","geometry":{"type":"Polygon","coordinates":[[[10.30322075,35.59817886],[10.59437084,35.50740051],[10.66295242,35.80425644],[10.53680515,36.36347198],[10.35482883,36.39509964],[10.19923019,36.16115189],[10.30322075,35.59817886]]]},"properties":{"GID_0":"TUN","NAME_0":"Tunisia","GID_1":"TUN.20_1","NAME_1":"Sousse","VARNAME_1":"Sousa|Sussa|Susse|Susa|Sūsah","NL_NAME_1":"","TYPE_1":"Wilayat","ENGTYPE_1":"Governorate","CC_1":"","HASC_1":"TN.SS","cXId":"SS"}},
{"type":"Feature","geometry":{"type":"Polygon","coordinates":[[[8.35474491,32.52820587],[9.06597614,32.08689117],[9.55729771,30.23681068],[9.88890266,30.34918785],[10.30777359,30.90897179],[10.14062023,31.49329758],[10.63912868,31.96794128],[11.14614964,32.25342941],[11.3445797,32.50769043],[11.06365871,32.69675064],[10.99125099,33.06560135],[10.50236893,33.27481079],[9.92028522,33.0891304],[9.66339874,32.80627823],[8.35474491,32.52820587]]]},"properties":{"GID_0":"TUN","NAME_0":"Tunisia","GID_1":"TUN.21_1","NAME_1":"Tataouine","VARNAME_1":"Foum Tataouine|Tatahouine|Tatuine|Taţāwīn","NL_NAME_1":"","TYPE_1":"Wilayat","ENGTYPE_1":"Governorate","CC_1":"","HASC_1":"TN.TA","cXId":"TA"}},
{"type":"Feature","geometry":{"type":"Polygon","coordinates":[[[7.75341892,33.43026352],[8.54672718,33.92374039],[8.65681171,34.08311844],[8.04351234,34.31679916],[8.12983704,34.52702713],[7.58077717,34.08573914],[7.75341892,33.43026352]]]},"properties":{"GID_0":"TUN","NAME_0":"Tunisia","GID_1":"TUN.22_1","NAME_1":"Tozeur","VARNAME_1":"Tawzar|Touzar|Tūzar","NL_NAME_1":"","TYPE_1":"Wilayat","ENGTYPE_1":"Governorate","CC_1":"","HASC_1":"TN.TO","cXId":"TO"}},
{"type":"Feature","geometry":{"type":"Polygon","coordinates":[[[10.04176044,36.72344971],[10.20784092,36.77902603],[10.2304163,36.95763779],[10.08026409,36.82851028],[10.04176044,36.72344971]]]},"properties":{"GID_0":"TUN","NAME_0":"Tunisia","GID_1":"TUN.23_1","NAME_1":"Tunis","VARNAME_1":"Tounis|Tunis City|Tūnus|Túnez|Túnis|Tunisi|Tūnis","NL_NAME_1":"","TYPE_1":"Wilayat","ENGTYPE_1":"Governorate","CC_1":"","HASC_1":"TN.TU","cXId":"TU"}},
{"type":"Feature","geometry":{"type":"Polygon","coordinates":[[[9.7273674,36.09008026],[10.19923019,36.16115189],[10.35482883,36.39509964],[10.33234119,36.50741959],[9.97170162,36.66345978],[9.84553814,36.59164047],[9.73458958,36.46102905],[9.7273674,36.09008026]]]},"properties":{"GID_0":"TUN","NAME_0":"Tunisia","GID_1":"TUN.24_1","NAME_1":"Zaghouan","VARNAME_1":"Tunis South|Zachouan|Zaguan|Zaghwān|Saghuan","NL_NAME_1":"","TYPE_1":"Wilayat","ENGTYPE_1":"Governorate","CC_1":"","HASC_1":"TN.ZA","cXId":"ZA"}}
]}